[
    {
        "name": "#1 Noah Atubolu",
        "position": "Вратарь",
        "age": 23,
        "height": 190,
        "stats": {
            "seasons": [],
            "total_stats": {
                "total_matches": 29,
                "total_goals": 0,
                "total_own_goals": 0,
                "total_substitutions_in": 0,
                "total_substitutions_out": 0,
                "total_yellow_cards": 0,
                "total_yellow_red_cards": 0,
                "total_red_cards": 0,
                "total_goals_conceded": 37,
                "total_clean_sheets": 9,
                "total_minutes_played": 0
            }
        },
        "url": "https://www.transfermarkt.world/-/leistungsdaten/spieler/526845/plus/1",
        "team": "Фрайбург"
    },
    {
        "name": "#21 Florian Müller",
        "position": "Вратарь",
        "age": 28,
        "height": 190,
        "stats": {
            "seasons": [],
            "total_stats": {
                "total_matches": 2,
                "total_goals": 0,
                "total_own_goals": 0,
                "total_substitutions_in": 0,
                "total_substitutions_out": 0,
                "total_yellow_cards": 1,
                "total_yellow_red_cards": 0,
                "total_red_cards": 0,
                "total_goals_conceded": 1,
                "total_clean_sheets": 1,
                "total_minutes_played": 180
            }
        },
        "url": "https://www.transfermarkt.world/-/leistungsdaten/spieler/284769/plus/1",
        "team": "Фрайбург"
    },
    {
        "name": "#24 Jannik Huth",
        "position": "Вратарь",
        "age": 31,
        "height": 185,
        "stats": {
            "seasons": [],
            "total_stats": {
                "total_matches": 0,
                "total_goals": 0,
                "total_own_goals": 0,
                "total_substitutions_in": 0,
                "total_substitutions_out": 0,
                "total_yellow_cards": 0,
                "total_yellow_red_cards": 0,
                "total_red_cards": 0,
                "total_goals_conceded": 0,
                "total_clean_sheets": 0,
                "total_minutes_played": 0
            }
        },
        "url": "https://www.transfermarkt.world/-/leistungsdaten/spieler/160954/plus/1",
        "team": "Фрайбург"
    },
    {
        "name": "#3 Philipp Lienhart",
        "position": "Центр. защитник",
        "age": 29,
        "height": 189,
        "stats": {
            "seasons": [],
            "total_stats": {
                "total_matches": 19,
                "total_goals": 1,
                "total_assists": 0,
                "total_own_goals": 0,
                "total_substitutions_in": 1,
                "total_substitutions_out": 4,
                "total_yellow_cards": 5,
                "total_yellow_red_cards": 1,
                "total_red_cards": 0,
                "total_penalty_goals": 0,
                "total_minutes_played": 0
            }
        },
        "url": "https://www.transfermarkt.world/-/leistungsdaten/spieler/225657/plus/1",
        "team": "Фрайбург"
    },
    {
        "name": "#37 Max Rosenfelder",
        "position": "Центр. защитник",
        "age": 22,
        "height": 186,
        "stats": {
            "seasons": [],
            "total_stats": {
                "total_matches": 17,
                "total_goals": 0,
                "total_assists": 0,
                "total_own_goals": 1,
                "total_substitutions_in": 9,
                "total_substitutions_out": 5,
                "total_yellow_cards": 1,
                "total_yellow_red_cards": 0,
                "total_red_cards": 0,
                "total_penalty_goals": 0,
                "total_minutes_played": 753
            }
        },
        "url": "https://www.transfermarkt.world/-/leistungsdaten/spieler/599419/plus/1",
        "team": "Фрайбург"
    },
    {
        "name": "#28 Matthias Ginter",
        "position": "Центр. защитник",
        "age": 32,
        "height": 189,
        "stats": {
            "seasons": [],
            "total_stats": {
                "total_matches": 30,
                "total_goals": 0,
                "total_assists": 4,
                "total_own_goals": 0,
                "total_substitutions_in": 0,
                "total_substitutions_out": 0,
                "total_yellow_cards": 1,
                "total_yellow_red_cards": 0,
                "total_red_cards": 0,
                "total_penalty_goals": 0,
                "total_minutes_played": 0
            }
        },
        "url": "https://www.transfermarkt.world/-/leistungsdaten/spieler/124502/plus/1",
        "team": "Фрайбург"
    },
    {
        "name": "#43 Bruno Ogbus",
        "position": "Центр. защитник",
        "age": 20,
        "height": 185,
        "stats": {
            "seasons": [],
            "total_stats": {
                "total_matches": 18,
                "total_goals": 0,
                "total_assists": 0,
                "total_own_goals": 0,
                "total_substitutions_in": 3,
                "total_substitutions_out": 6,
                "total_yellow_cards": 1,
                "total_yellow_red_cards": 0,
                "total_red_cards": 0,
                "total_penalty_goals": 0,
                "total_minutes_played": 0
            }
        },
        "url": "https://www.transfermarkt.world/-/leistungsdaten/spieler/863759/plus/1",
        "team": "Фрайбург"
    },
    {
        "name": "#5 Anthony Jung",
        "position": "Центр. защитник",
        "age": 34,
        "height": 186,
        "stats": {
            "seasons": [],
            "total_stats": {
                "total_matches": 11,
                "total_goals": 0,
                "total_assists": 0,
                "total_own_goals": 0,
                "total_substitutions_in": 6,
                "total_substitutions_out": 1,
                "total_yellow_cards": 2,
                "total_yellow_red_cards": 0,
                "total_red_cards": 0,
                "total_penalty_goals": 0,
                "total_minutes_played": 541
            }
        },
        "url": "https://www.transfermarkt.world/-/leistungsdaten/spieler/58995/plus/1",
        "team": "Фрайбург"
    },
    {
        "name": "#33 Jordy Makengo",
        "position": "Левый защитник",
        "age": 24,
        "height": 191,
        "stats": {
            "seasons": [],
            "total_stats": {
                "total_matches": 17,
                "total_goals": 0,
                "total_assists": 0,
                "total_own_goals": 0,
                "total_substitutions_in": 6,
                "total_substitutions_out": 3,
                "total_yellow_cards": 2,
                "total_yellow_red_cards": 0,
                "total_red_cards": 0,
                "total_penalty_goals": 0,
                "total_minutes_played": 0
            }
        },
        "url": "https://www.transfermarkt.world/-/leistungsdaten/spieler/815078/plus/1",
        "team": "Фрайбург"
    },
    {
        "name": "#30 Christian Günter",
        "position": "Левый защитник",
        "age": 32,
        "height": 184,
        "stats": {
            "seasons": [],
            "total_stats": {
                "total_matches": 23,
                "total_goals": 0,
                "total_assists": 5,
                "total_own_goals": 0,
                "total_substitutions_in": 6,
                "total_substitutions_out": 8,
                "total_yellow_cards": 3,
                "total_yellow_red_cards": 0,
                "total_red_cards": 0,
                "total_penalty_goals": 0,
                "total_minutes_played": 0
            }
        },
        "url": "https://www.transfermarkt.world/-/leistungsdaten/spieler/93707/plus/1",
        "team": "Фрайбург"
    },
    {
        "name": "#29 Philipp Treu",
        "position": "Правый защитник",
        "age": 25,
        "height": 173,
        "stats": {
            "seasons": [],
            "total_stats": {
                "total_matches": 26,
                "total_goals": 1,
                "total_assists": 1,
                "total_own_goals": 0,
                "total_substitutions_in": 7,
                "total_substitutions_out": 6,
                "total_yellow_cards": 3,
                "total_yellow_red_cards": 0,
                "total_red_cards": 0,
                "total_penalty_goals": 0,
                "total_minutes_played": 0
            }
        },
        "url": "https://www.transfermarkt.world/-/leistungsdaten/spieler/335993/plus/1",
        "team": "Фрайбург"
    },
    {
        "name": "#17 Lukas Kübler",
        "position": "Правый защитник",
        "age": 33,
        "height": 182,
        "stats": {
            "seasons": [],
            "total_stats": {
                "total_matches": 23,
                "total_goals": 2,
                "total_assists": 1,
                "total_own_goals": 0,
                "total_substitutions_in": 2,
                "total_substitutions_out": 9,
                "total_yellow_cards": 4,
                "total_yellow_red_cards": 0,
                "total_red_cards": 0,
                "total_penalty_goals": 0,
                "total_minutes_played": 0
            }
        },
        "url": "https://www.transfermarkt.world/-/leistungsdaten/spieler/93604/plus/1",
        "team": "Фрайбург"
    },
    {
        "name": "#6 Patrick Osterhage",
        "position": "Опорный полузащитник",
        "age": 26,
        "height": 186,
        "stats": {
            "seasons": [],
            "total_stats": {
                "total_matches": 23,
                "total_goals": 2,
                "total_assists": 0,
                "total_own_goals": 0,
                "total_substitutions_in": 9,
                "total_substitutions_out": 6,
                "total_yellow_cards": 4,
                "total_yellow_red_cards": 0,
                "total_red_cards": 0,
                "total_penalty_goals": 0,
                "total_minutes_played": 0
            }
        },
        "url": "https://www.transfermarkt.world/-/leistungsdaten/spieler/443331/plus/1",
        "team": "Фрайбург"
    },
    {
        "name": "#27 Nicolas Höfler",
        "position": "Опорный полузащитник",
        "age": 35,
        "height": 181,
        "stats": {
            "seasons": [],
            "total_stats": {
                "total_matches": 9,
                "total_goals": 0,
                "total_assists": 0,
                "total_own_goals": 0,
                "total_substitutions_in": 9,
                "total_substitutions_out": 0,
                "total_yellow_cards": 1,
                "total_yellow_red_cards": 0,
                "total_red_cards": 0,
                "total_penalty_goals": 0,
                "total_minutes_played": 135
            }
        },
        "url": "https://www.transfermarkt.world/-/leistungsdaten/spieler/55099/plus/1",
        "team": "Фрайбург"
    },
    {
        "name": "#44 Johan Manzambi",
        "position": "Центр. полузащитник",
        "age": 20,
        "height": 182,
        "stats": {
            "seasons": [],
            "total_stats": {
                "total_matches": 28,
                "total_goals": 4,
                "total_assists": 5,
                "total_own_goals": 0,
                "total_substitutions_in": 3,
                "total_substitutions_out": 18,
                "total_yellow_cards": 4,
                "total_yellow_red_cards": 0,
                "total_red_cards": 1,
                "total_penalty_goals": 0,
                "total_minutes_played": 0
            }
        },
        "url": "https://www.transfermarkt.world/-/leistungsdaten/spieler/927353/plus/1",
        "team": "Фрайбург"
    },
    {
        "name": "#8 Maximilian Eggestein",
        "position": "Центр. полузащитник",
        "age": 29,
        "height": 181,
        "stats": {
            "seasons": [],
            "total_stats": {
                "total_matches": 31,
                "total_goals": 3,
                "total_assists": 0,
                "total_own_goals": 0,
                "total_substitutions_in": 0,
                "total_substitutions_out": 1,
                "total_yellow_cards": 3,
                "total_yellow_red_cards": 0,
                "total_red_cards": 1,
                "total_penalty_goals": 0,
                "total_minutes_played": 0
            }
        },
        "url": "https://www.transfermarkt.world/-/leistungsdaten/spieler/190284/plus/1",
        "team": "Фрайбург"
    },
    {
        "name": "#11 Daniel-Kofi Kyereh",
        "position": "Атак. полузащитник",
        "age": 29,
        "height": 179,
        "stats": {
            "seasons": [],
            "total_stats": {
                "total_matches": 227,
                "total_goals": 67,
                "total_assists": 47,
                "total_own_goals": 1,
                "total_substitutions_in": 41,
                "total_substitutions_out": 96,
                "total_yellow_cards": 36,
                "total_yellow_red_cards": 1,
                "total_red_cards": 1,
                "total_penalty_goals": 2,
                "total_minutes_played": 0
            }
        },
        "url": "https://www.transfermarkt.world/-/leistungsdaten/spieler/272587/plus/1",
        "team": "Фрайбург"
    },
    {
        "name": "#7 Derry Scherhant",
        "position": "Левый Вингер",
        "age": 23,
        "height": 185,
        "stats": {
            "seasons": [],
            "total_stats": {
                "total_matches": 27,
                "total_goals": 6,
                "total_assists": 1,
                "total_own_goals": 0,
                "total_substitutions_in": 20,
                "total_substitutions_out": 7,
                "total_yellow_cards": 1,
                "total_yellow_red_cards": 0,
                "total_red_cards": 0,
                "total_penalty_goals": 0,
                "total_minutes_played": 941
            }
        },
        "url": "https://www.transfermarkt.world/-/leistungsdaten/spieler/820957/plus/1",
        "team": "Фрайбург"
    },
    {
        "name": "#32 Vincenzo Grifo",
        "position": "Левый Вингер",
        "age": 32,
        "height": 180,
        "stats": {
            "seasons": [],
            "total_stats": {
                "total_matches": 31,
                "total_goals": 10,
                "total_assists": 3,
                "total_own_goals": 0,
                "total_substitutions_in": 9,
                "total_substitutions_out": 20,
                "total_yellow_cards": 1,
                "total_yellow_red_cards": 0,
                "total_red_cards": 0,
                "total_penalty_goals": 6,
                "total_minutes_played": 0
            }
        },
        "url": "https://www.transfermarkt.world/-/leistungsdaten/spieler/185077/plus/1",
        "team": "Фрайбург"
    },
    {
        "name": "#22 Cyriaque Irié",
        "position": "Правый Вингер",
        "age": 20,
        "height": 185,
        "stats": {
            "seasons": [],
            "total_stats": {
                "total_matches": 4,
                "total_goals": 0,
                "total_assists": 0,
                "total_own_goals": 0,
                "total_substitutions_in": 4,
                "total_substitutions_out": 0,
                "total_yellow_cards": 1,
                "total_yellow_red_cards": 0,
                "total_red_cards": 0,
                "total_penalty_goals": 0,
                "total_minutes_played": 81
            }
        },
        "url": "https://www.transfermarkt.world/-/leistungsdaten/spieler/1145064/plus/1",
        "team": "Фрайбург"
    },
    {
        "name": "#19 Niklas Beste",
        "position": "Правый Вингер",
        "age": 27,
        "height": 175,
        "stats": {
            "seasons": [],
            "total_stats": {
                "total_matches": 26,
                "total_goals": 0,
                "total_assists": 4,
                "total_own_goals": 0,
                "total_substitutions_in": 5,
                "total_substitutions_out": 15,
                "total_yellow_cards": 4,
                "total_yellow_red_cards": 0,
                "total_red_cards": 0,
                "total_penalty_goals": 0,
                "total_minutes_played": 0
            }
        },
        "url": "https://www.transfermarkt.world/-/leistungsdaten/spieler/342967/plus/1",
        "team": "Фрайбург"
    },
    {
        "name": "#14 Yuito Suzuki",
        "position": "Оттянутый нап.",
        "age": 24,
        "height": 175,
        "stats": {
            "seasons": [],
            "total_stats": {
                "total_matches": 24,
                "total_goals": 4,
                "total_assists": 6,
                "total_own_goals": 0,
                "total_substitutions_in": 5,
                "total_substitutions_out": 13,
                "total_yellow_cards": 3,
                "total_yellow_red_cards": 0,
                "total_red_cards": 0,
                "total_penalty_goals": 0,
                "total_minutes_played": 0
            }
        },
        "url": "https://www.transfermarkt.world/-/leistungsdaten/spieler/668606/plus/1",
        "team": "Фрайбург"
    },
    {
        "name": "#26 Maximilian Philipp",
        "position": "Оттянутый нап.",
        "age": 31,
        "height": 183,
        "stats": {
            "seasons": [],
            "total_stats": {
                "total_matches": 0,
                "total_goals": 0,
                "total_assists": 0,
                "total_own_goals": 0,
                "total_substitutions_in": 0,
                "total_substitutions_out": 0,
                "total_yellow_cards": 0,
                "total_yellow_red_cards": 0,
                "total_red_cards": 0,
                "total_penalty_goals": 0,
                "total_minutes_played": 0
            }
        },
        "url": "https://www.transfermarkt.world/-/leistungsdaten/spieler/143891/plus/1",
        "team": "Фрайбург"
    },
    {
        "name": "#31 Igor Matanovic",
        "position": "Центральный нап.",
        "age": 22,
        "height": 194,
        "stats": {
            "seasons": [],
            "total_stats": {
                "total_matches": 27,
                "total_goals": 7,
                "total_assists": 1,
                "total_own_goals": 0,
                "total_substitutions_in": 22,
                "total_substitutions_out": 3,
                "total_yellow_cards": 1,
                "total_yellow_red_cards": 0,
                "total_red_cards": 0,
                "total_penalty_goals": 1,
                "total_minutes_played": 853
            }
        },
        "url": "https://www.transfermarkt.world/-/leistungsdaten/spieler/605268/plus/1",
        "team": "Фрайбург"
    },
    {
        "name": "#9 Lucas Höler",
        "position": "Центральный нап.",
        "age": 31,
        "height": 184,
        "stats": {
            "seasons": [],
            "total_stats": {
                "total_matches": 25,
                "total_goals": 3,
                "total_assists": 3,
                "total_own_goals": 0,
                "total_substitutions_in": 7,
                "total_substitutions_out": 12,
                "total_yellow_cards": 0,
                "total_yellow_red_cards": 0,
                "total_red_cards": 0,
                "total_penalty_goals": 0,
                "total_minutes_played": 0
            }
        },
        "url": "https://www.transfermarkt.world/-/leistungsdaten/spieler/248999/plus/1",
        "team": "Фрайбург"
    }
]